odoo8_addon_l10n_br_data_account_product-8.0.1.0.0.99.dev8-py2.7-nspkg.pth
odoo8_addon_l10n_br_data_account_product-8.0.1.0.0.99.dev8.dist-info/METADATA
odoo8_addon_l10n_br_data_account_product-8.0.1.0.0.99.dev8.dist-info/RECORD
odoo8_addon_l10n_br_data_account_product-8.0.1.0.0.99.dev8.dist-info/WHEEL
odoo8_addon_l10n_br_data_account_product-8.0.1.0.0.99.dev8.dist-info/namespace_packages.txt
odoo8_addon_l10n_br_data_account_product-8.0.1.0.0.99.dev8.dist-info/top_level.txt
odoo_addons/l10n_br_data_account_product/README.rst
odoo_addons/l10n_br_data_account_product/__init__.py
odoo_addons/l10n_br_data_account_product/__openerp__.py
odoo_addons/l10n_br_data_account_product/data/account.product.fiscal.classification.template.csv
odoo_addons/l10n_br_data_account_product/data/l10n_br_account_product.cest.csv
odoo_addons/l10n_br_data_account_product/data/l10n_br_account_product.icms_relief.csv
odoo_addons/l10n_br_data_account_product/data/l10n_br_account_product.ipi_guideline.csv
odoo_addons/l10n_br_data_account_product/demo/l10n_br_data_account_product_demo.xml
odoo_addons/l10n_br_data_account_product/i18n/pt_BR.po
odoo_addons/l10n_br_data_account_product/static/description/icon.png
